{
    "rules": {
        "primaryKeys": [
            "Id"
        ]
    },
    "data": [
        {
            "Id": 900010101,
            "Name": "タンクA-1",
            "Description": "タンクA-1"
        },
        {
            "Id": 900010102,
            "Name": "タンクA-2",
            "Description": "タンクA-2"
        },
        {
            "Id": 900010103,
            "Name": "タンクA-3",
            "Description": "タンクA-3"
        },
        {
            "Id": 900010201,
            "Name": "タンクB-1",
            "Description": "タンクB-1"
        },
        {
            "Id": 900010202,
            "Name": "タンクB-2",
            "Description": "タンクB-2"
        },
        {
            "Id": 900010203,
            "Name": "タンクB-3",
            "Description": "タンクB-3"
        },
        {
            "Id": 900010301,
            "Name": "タンクC-1",
            "Description": "タンクC-1"
        },
        {
            "Id": 900010302,
            "Name": "タンクC-2",
            "Description": "タンクC-2"
        },
        {
            "Id": 900010303,
            "Name": "タンクC-3",
            "Description": "タンクC-3"
        },
        {
            "Id": 900020101,
            "Name": "おひさまプラン-1",
            "Description": "おひさまプラン-1"
        },
        {
            "Id": 900020102,
            "Name": "おひさまプラン-2",
            "Description": "おひさまプラン-2"
        },
        {
            "Id": 900020103,
            "Name": "おひさまプラン-3",
            "Description": "おひさまプラン-3"
        },
        {
            "Id": 900020201,
            "Name": "おつきさまプラン-1",
            "Description": "おつきさまプラン-1"
        },
        {
            "Id": 900020202,
            "Name": "おつきさまプラン-2",
            "Description": "おつきさまプラン-2"
        },
        {
            "Id": 900020203,
            "Name": "おつきさまプラン-3",
            "Description": "おつきさまプラン-3"
        },
        {
            "Id": 900020301,
            "Name": "おほしさまプラン-1",
            "Description": "おほしさまプラン-1"
        },
        {
            "Id": 900020302,
            "Name": "おほしさまプラン-2",
            "Description": "おほしさまプラン-2"
        },
        {
            "Id": 900020303,
            "Name": "おほしさまプラン-3",
            "Description": "おほしさまプラン-3"
        }
    ]
}