[
  {
    "raw": "1日1回 PARTY! LIMITED COLLECTION EXTRA 無料10連ガチャキャンペーン",
    "translation": {
      "zh-CN": {
        "text": "",
        "author": ""
      },
      "en": {
        "text": "",
        "author": ""
      }
    }
  },
  {
    "raw": "1日1回 PARTY! LIMITED COLLECTION 無料10連ガチャキャンペーン",
    "translation": {
      "zh-CN": {
        "text": "",
        "author": ""
      },
      "en": {
        "text": "",
        "author": ""
      }
    }
  },
  {
    "raw": "1日1回 SPRING LIMITED COLLECTION MEMORY REVIVAL 無料10連ガチャキャンペーン",
    "translation": {
      "zh-CN": {
        "text": "",
        "author": ""
      },
      "en": {
        "text": "",
        "author": ""
      }
    }
  },
  {
    "raw": "1日1回無料10連ガチャキャンペーン",
    "translation": {
      "zh-CN": {
        "text": "",
        "author": ""
      },
      "en": {
        "text": "",
        "author": ""
      }
    }
  },
  {
    "raw": "1日1回無料ガチャキャンペーン",
    "translation": {
      "zh-CN": {
        "text": "",
        "author": ""
      },
      "en": {
        "text": "",
        "author": ""
      }
    }
  },
  {
    "raw": "PARTY!開催記念キャンペーン",
    "translation": {
      "zh-CN": {
        "text": "",
        "author": ""
      },
      "en": {
        "text": "",
        "author": ""
      }
    }
  },
  {
    "raw": "無料10連キャンペーン",
    "translation": {
      "zh-CN": {
        "text": "",
        "author": ""
      },
      "en": {
        "text": "",
        "author": ""
      }
    }
  },
  {
    "raw": "謹賀新年！今年もリンクラ！スペシャルキャンペーン",
    "translation": {
      "zh-CN": {
        "text": "",
        "author": ""
      },
      "en": {
        "text": "",
        "author": ""
      }
    }
  }
]